[{"line":1,"elements":[{"line":3,"name":"","description":"","type":"background","keyword":"Background","steps":[{"name":"url userApiUrl","result":{"duration":7541,"status":"passed"},"match":{"location":"karate","arguments":[]},"keyword":"*","line":4,"doc_string":{"content_type":"","value":"15:28:02.995 Environment variable is : popcorn \n","line":4}},{"name":"header Content-Type = 'application\/json-patch+json'","result":{"duration":188375,"status":"passed"},"match":{"location":"karate","arguments":[]},"keyword":"*","line":5},{"name":"header accept = '*\/*'","result":{"duration":45833,"status":"passed"},"match":{"location":"karate","arguments":[]},"keyword":"*","line":6},{"name":"def randomString = Java.type('utils.RandomValue')","result":{"duration":10979083,"status":"passed"},"match":{"location":"karate","arguments":[]},"keyword":"*","line":8},{"name":"def randomEmailValue = new randomString().createRandomString(7,\"email\");","result":{"duration":32579500,"status":"passed"},"match":{"location":"karate","arguments":[]},"keyword":"*","line":9},{"name":"def randomStringValue = new randomString().createRandomString(7,\"string\");","result":{"duration":2697417,"status":"passed"},"match":{"location":"karate","arguments":[]},"keyword":"*","line":10},{"name":"def randomIntValue = new randomString().createInt(10);","result":{"duration":7206792,"status":"passed"},"match":{"location":"karate","arguments":[]},"keyword":"*","line":11}]},{"line":14,"name":"Customer Create - Success Scenario","description":"","id":"customer-create---success-scenario","type":"scenario","keyword":"Scenario","steps":[{"name":"path '\/Customer\/Create'","result":{"duration":295625,"status":"passed"},"match":{"location":"karate","arguments":[]},"keyword":"Given","line":15},{"name":"header Authorization = 'Bearer ' + consoleAuthorization","result":{"duration":144084,"status":"passed"},"match":{"location":"karate","arguments":[]},"keyword":"And","line":16},{"name":"def customerCreateInfo =","result":{"duration":293208,"status":"passed"},"match":{"location":"karate","arguments":[]},"keyword":"*","line":17,"doc_string":{"content_type":"","value":"{\n   \"fullName\": \"#(randomStringValue)\",\n   \"phoneCountryId\": \"59c4edba-f347-45b3-a5c9-aed7ac852ff8\",\n   \"email\": \"#(randomEmailValue)\",\n   \"phoneNumber\": \"#(randomIntValue)\"\n}","line":17}},{"name":"request customerCreateInfo","result":{"duration":4459,"status":"passed"},"match":{"location":"karate","arguments":[]},"keyword":"And","line":26},{"name":"method POST","result":{"duration":1012931417,"status":"passed"},"match":{"location":"karate","arguments":[]},"keyword":"When","line":27},{"name":"status 200","result":{"duration":451500,"status":"passed"},"match":{"location":"karate","arguments":[]},"keyword":"Then","line":28},{"name":"print 'customer create response -->',response","result":{"duration":11955459,"status":"passed"},"match":{"location":"karate","arguments":[]},"keyword":"Then","line":29,"doc_string":{"content_type":"","value":"15:28:04.074 [print] customer create response --> {\n  \"lastName\": \"\",\n  \"deliveryAddresses\": [\n  ],\n  \"imagePath\": null,\n  \"roles\": [\n  ],\n  \"lastOrderDate\": null,\n  \"registerType\": 0,\n  \"phoneCountry\": {\n    \"name\": \"Russian Federation\",\n    \"id\": \"59c4edba-f347-45b3-a5c9-aed7ac852ff8\"\n  },\n  \"customerStatus\": 0,\n  \"riderId\": null,\n  \"password\": null,\n  \"passwordConfirm\": null,\n  \"imageFile\": null,\n  \"referralCode\": null,\n  \"imageUrl\": null,\n  \"customerId\": null,\n  \"id\": \"0bec4e41-4e3b-4e71-99a3-9559d103ba83\",\n  \"nationalSecurityNumber\": null,\n  \"email\": \"etjv42h@grr.la\",\n  \"isBlockedCodeCampaign\": false,\n  \"fullName\": \"uetwgdd\",\n  \"employeeId\": null,\n  \"userId\": \"b3fe52c5-069f-4bf7-bbd3-955d95d98af4\",\n  \"lastActiveAt\": \"0001-01-01T00:00:00.000Z\",\n  \"firstName\": \"uetwgdd\",\n  \"phoneNumber\": \"3831264501\",\n  \"roleIds\": null,\n  \"statusText\": \"Active\",\n  \"orders\": null,\n  \"lastActiveIp\": null,\n  \"residenceAddress\": null,\n  \"status\": 1\n}\n \n","line":29}},{"name":"match $.status == 1","result":{"duration":1148666,"status":"passed"},"match":{"location":"karate","arguments":[]},"keyword":"Then","line":30},{"name":"match $.statusText == \"Active\"","result":{"duration":126916,"status":"passed"},"match":{"location":"karate","arguments":[]},"keyword":"Then","line":31},{"name":"match $.customerStatus == 0","result":{"duration":76750,"status":"passed"},"match":{"location":"karate","arguments":[]},"keyword":"Then","line":32},{"name":"match $.email == customerCreateInfo.email","result":{"duration":1569458,"status":"passed"},"match":{"location":"karate","arguments":[]},"keyword":"Then","line":33},{"name":"match $.fullName == customerCreateInfo.fullName","result":{"duration":1807667,"status":"passed"},"match":{"location":"karate","arguments":[]},"keyword":"Then","line":34},{"name":"match $.phoneNumber == customerCreateInfo.phoneNumber","result":{"duration":821917,"status":"passed"},"match":{"location":"karate","arguments":[]},"keyword":"Then","line":35},{"name":"match $.phoneCountry.id == customerCreateInfo.phoneCountryId","result":{"duration":819625,"status":"passed"},"match":{"location":"karate","arguments":[]},"keyword":"Then","line":36},{"name":"match $.phoneCountry.name == '#string'","result":{"duration":282584,"status":"passed"},"match":{"location":"karate","arguments":[]},"keyword":"Then","line":39},{"name":"match $.phoneCountry.id == '#string'","result":{"duration":246625,"status":"passed"},"match":{"location":"karate","arguments":[]},"keyword":"Then","line":40},{"name":"match $.customerStatus == '#number'","result":{"duration":337375,"status":"passed"},"match":{"location":"karate","arguments":[]},"keyword":"Then","line":41},{"name":"match $.email == '#string'","result":{"duration":68083,"status":"passed"},"match":{"location":"karate","arguments":[]},"keyword":"Then","line":42},{"name":"match $.id == '#string'","result":{"duration":46000,"status":"passed"},"match":{"location":"karate","arguments":[]},"keyword":"Then","line":43},{"name":"match $.fullName == '#string'","result":{"duration":36583,"status":"passed"},"match":{"location":"karate","arguments":[]},"keyword":"Then","line":44},{"name":"match $.userId == '#string'","result":{"duration":79167,"status":"passed"},"match":{"location":"karate","arguments":[]},"keyword":"Then","line":45},{"name":"match $.firstName == '#string'","result":{"duration":84166,"status":"passed"},"match":{"location":"karate","arguments":[]},"keyword":"Then","line":46},{"name":"match $.phoneNumber == '#string'","result":{"duration":43458,"status":"passed"},"match":{"location":"karate","arguments":[]},"keyword":"Then","line":47},{"name":"match $.statusText == '#string'","result":{"duration":37417,"status":"passed"},"match":{"location":"karate","arguments":[]},"keyword":"Then","line":48},{"name":"match $.status == '#number'","result":{"duration":179916,"status":"passed"},"match":{"location":"karate","arguments":[]},"keyword":"Then","line":49},{"name":"match response.referralCode == '#null'","result":{"duration":204542,"status":"passed"},"match":{"location":"karate","arguments":[]},"keyword":"*","line":52},{"name":"match $.customerId == '#null'","result":{"duration":59416,"status":"passed"},"match":{"location":"karate","arguments":[]},"keyword":"Then","line":53},{"name":"match $.riderId == '#null'","result":{"duration":46750,"status":"passed"},"match":{"location":"karate","arguments":[]},"keyword":"Then","line":54},{"name":"match $.password == '#null'","result":{"duration":58000,"status":"passed"},"match":{"location":"karate","arguments":[]},"keyword":"Then","line":55},{"name":"match $.nationalSecurityNumber == '#null'","result":{"duration":50291,"status":"passed"},"match":{"location":"karate","arguments":[]},"keyword":"Then","line":56},{"name":"match $.employeeId == '#null'","result":{"duration":43459,"status":"passed"},"match":{"location":"karate","arguments":[]},"keyword":"Then","line":57},{"name":"match $.roleIds == '#null'","result":{"duration":42959,"status":"passed"},"match":{"location":"karate","arguments":[]},"keyword":"Then","line":58},{"name":"match $.orders == '#null'","result":{"duration":43709,"status":"passed"},"match":{"location":"karate","arguments":[]},"keyword":"Then","line":59}],"tags":[{"name":"@customerInfo","line":13}]},{"line":3,"name":"","description":"","type":"background","keyword":"Background","steps":[{"name":"url userApiUrl","result":{"duration":7417,"status":"passed"},"match":{"location":"karate","arguments":[]},"keyword":"*","line":4,"doc_string":{"content_type":"","value":"15:28:03.154 Environment variable is : popcorn \n","line":4}},{"name":"header Content-Type = 'application\/json-patch+json'","result":{"duration":98750,"status":"passed"},"match":{"location":"karate","arguments":[]},"keyword":"*","line":5},{"name":"header accept = '*\/*'","result":{"duration":39375,"status":"passed"},"match":{"location":"karate","arguments":[]},"keyword":"*","line":6},{"name":"def randomString = Java.type('utils.RandomValue')","result":{"duration":461459,"status":"passed"},"match":{"location":"karate","arguments":[]},"keyword":"*","line":8},{"name":"def randomEmailValue = new randomString().createRandomString(7,\"email\");","result":{"duration":269042,"status":"passed"},"match":{"location":"karate","arguments":[]},"keyword":"*","line":9},{"name":"def randomStringValue = new randomString().createRandomString(7,\"string\");","result":{"duration":158875,"status":"passed"},"match":{"location":"karate","arguments":[]},"keyword":"*","line":10},{"name":"def randomIntValue = new randomString().createInt(10);","result":{"duration":209416,"status":"passed"},"match":{"location":"karate","arguments":[]},"keyword":"*","line":11}]},{"line":63,"name":"Customer Create - Without Authorization","description":"","id":"customer-create---without-authorization","type":"scenario","keyword":"Scenario","steps":[{"name":"path '\/Customer\/Create'","result":{"duration":103916,"status":"passed"},"match":{"location":"karate","arguments":[]},"keyword":"Given","line":64},{"name":"def customerCreateInfo =","result":{"duration":1331084,"status":"passed"},"match":{"location":"karate","arguments":[]},"keyword":"*","line":65,"doc_string":{"content_type":"","value":"{\n   \"fullName\": \"#(randomStringValue)\",\n   \"phoneCountryId\": \"59c4edba-f347-45b3-a5c9-aed7ac852ff8\",\n   \"email\": \"#(randomEmailValue)\",\n   \"phoneNumber\": \"#(randomIntValue)\"\n}","line":65}},{"name":"request customerCreateInfo","result":{"duration":5000,"status":"passed"},"match":{"location":"karate","arguments":[]},"keyword":"And","line":74},{"name":"method POST","result":{"duration":582079792,"status":"passed"},"match":{"location":"karate","arguments":[]},"keyword":"When","line":75},{"name":"status 401","result":{"duration":6209,"status":"passed"},"match":{"location":"karate","arguments":[]},"keyword":"Then","line":76},{"name":"print 'customer create without authorization response -->',response","result":{"duration":3655916,"status":"passed"},"match":{"location":"karate","arguments":[]},"keyword":"Then","line":77,"doc_string":{"content_type":"","value":"15:28:03.743 [print] customer create without authorization response --> {\n  \"visible\": true,\n  \"action\": \"default\",\n  \"messages\": [\n    \"User Authorization Error\"\n  ],\n  \"type\": \"authorization\",\n  \"title\": null,\n  \"message\": \"User Authorization Error\",\n  \"typeCode\": 401\n}\n \n","line":77}},{"name":"match response.messages[0] == 'User Authorization Error'","result":{"duration":2728959,"status":"passed"},"match":{"location":"karate","arguments":[]},"keyword":"And","line":78},{"name":"assert response.message == 'User Authorization Error'","result":{"duration":988375,"status":"passed"},"match":{"location":"karate","arguments":[]},"keyword":"And","line":79},{"name":"assert response.typeCode == 401","result":{"duration":1258875,"status":"passed"},"match":{"location":"karate","arguments":[]},"keyword":"And","line":80}],"tags":[]},{"line":3,"name":"","description":"","type":"background","keyword":"Background","steps":[{"name":"url userApiUrl","result":{"duration":25875,"status":"passed"},"match":{"location":"karate","arguments":[]},"keyword":"*","line":4,"doc_string":{"content_type":"","value":"15:28:03.540 Environment variable is : popcorn \n","line":4}},{"name":"header Content-Type = 'application\/json-patch+json'","result":{"duration":360667,"status":"passed"},"match":{"location":"karate","arguments":[]},"keyword":"*","line":5},{"name":"header accept = '*\/*'","result":{"duration":18000,"status":"passed"},"match":{"location":"karate","arguments":[]},"keyword":"*","line":6},{"name":"def randomString = Java.type('utils.RandomValue')","result":{"duration":504042,"status":"passed"},"match":{"location":"karate","arguments":[]},"keyword":"*","line":8},{"name":"def randomEmailValue = new randomString().createRandomString(7,\"email\");","result":{"duration":538625,"status":"passed"},"match":{"location":"karate","arguments":[]},"keyword":"*","line":9},{"name":"def randomStringValue = new randomString().createRandomString(7,\"string\");","result":{"duration":282834,"status":"passed"},"match":{"location":"karate","arguments":[]},"keyword":"*","line":10},{"name":"def randomIntValue = new randomString().createInt(10);","result":{"duration":440375,"status":"passed"},"match":{"location":"karate","arguments":[]},"keyword":"*","line":11}]},{"line":104,"name":"Customer Create - Fail Scenarios","description":"","id":"customer-create---fail-scenarios","type":"scenario","keyword":"Scenario Outline","steps":[{"name":"path '\/Customer\/Create'","result":{"duration":147750,"status":"passed"},"match":{"location":"karate","arguments":[]},"keyword":"Given","line":85},{"name":"header Authorization = 'Bearer ' + consoleAuthorization","result":{"duration":180125,"status":"passed"},"match":{"location":"karate","arguments":[]},"keyword":"And","line":86},{"name":"def customerCreateInfo =","result":{"duration":4468375,"status":"passed"},"match":{"location":"karate","arguments":[]},"keyword":"*","line":87,"doc_string":{"content_type":"","value":"{\n   \"fullName\": \"#(randomStringValue)\",\n   \"phoneCountryId\": \"59c4edba-f347-45b3-a5c9-aed7ac852ff8\",\n   \"email\": \"\",\n   \"phoneNumber\": \"#(randomIntValue)\"\n}","line":87}},{"name":"request customerCreateInfo","result":{"duration":12083,"status":"passed"},"match":{"location":"karate","arguments":[]},"keyword":"And","line":96},{"name":"method POST","result":{"duration":967799750,"status":"passed"},"match":{"location":"karate","arguments":[]},"keyword":"When","line":97},{"name":"status 400","result":{"duration":49833,"status":"passed"},"match":{"location":"karate","arguments":[]},"keyword":"Then","line":98},{"name":"print 'customer create with wrong data response -->',response","result":{"duration":8304625,"status":"passed"},"match":{"location":"karate","arguments":[]},"keyword":"Then","line":99,"doc_string":{"content_type":"","value":"15:28:04.526 [print] customer create with wrong data response --> {\n  \"visible\": true,\n  \"action\": \"default\",\n  \"messages\": [\n    \"Email.NotValid\",\n    \"be.user.length\"\n  ],\n  \"validations\": {\n    \"email\": [\n      \"Email.NotValid\",\n      \"be.user.length\"\n    ]\n  },\n  \"type\": \"validation\",\n  \"title\": null,\n  \"message\": \"Email.NotValid\",\n  \"typeCode\": 400\n}\n \n","line":99}},{"name":"match response.message contains 'Email.NotValid'","result":{"duration":5563625,"status":"passed"},"match":{"location":"karate","arguments":[]},"keyword":"Then","line":100}],"tags":[]},{"line":3,"name":"","description":"","type":"background","keyword":"Background","steps":[{"name":"url userApiUrl","result":{"duration":12375,"status":"passed"},"match":{"location":"karate","arguments":[]},"keyword":"*","line":4,"doc_string":{"content_type":"","value":"15:28:03.752 Environment variable is : popcorn \n","line":4}},{"name":"header Content-Type = 'application\/json-patch+json'","result":{"duration":78917,"status":"passed"},"match":{"location":"karate","arguments":[]},"keyword":"*","line":5},{"name":"header accept = '*\/*'","result":{"duration":15208,"status":"passed"},"match":{"location":"karate","arguments":[]},"keyword":"*","line":6},{"name":"def randomString = Java.type('utils.RandomValue')","result":{"duration":290166,"status":"passed"},"match":{"location":"karate","arguments":[]},"keyword":"*","line":8},{"name":"def randomEmailValue = new randomString().createRandomString(7,\"email\");","result":{"duration":1050292,"status":"passed"},"match":{"location":"karate","arguments":[]},"keyword":"*","line":9},{"name":"def randomStringValue = new randomString().createRandomString(7,\"string\");","result":{"duration":699542,"status":"passed"},"match":{"location":"karate","arguments":[]},"keyword":"*","line":10},{"name":"def randomIntValue = new randomString().createInt(10);","result":{"duration":475875,"status":"passed"},"match":{"location":"karate","arguments":[]},"keyword":"*","line":11}]},{"line":105,"name":"Customer Create - Fail Scenarios","description":"","id":"customer-create---fail-scenarios","type":"scenario","keyword":"Scenario Outline","steps":[{"name":"path '\/Customer\/Create'","result":{"duration":130959,"status":"passed"},"match":{"location":"karate","arguments":[]},"keyword":"Given","line":85},{"name":"header Authorization = 'Bearer ' + consoleAuthorization","result":{"duration":1332292,"status":"passed"},"match":{"location":"karate","arguments":[]},"keyword":"And","line":86},{"name":"def customerCreateInfo =","result":{"duration":690375,"status":"passed"},"match":{"location":"karate","arguments":[]},"keyword":"*","line":87,"doc_string":{"content_type":"","value":"{\n   \"fullName\": \"#(randomStringValue)\",\n   \"phoneCountryId\": \"59c4edba-f347-45b3-a5c9-aed7ac852ff8\",\n   \"email\": \"#(randomEmailValue)\",\n   \"phoneNumber\": \"\"\n}","line":87}},{"name":"request customerCreateInfo","result":{"duration":4458,"status":"passed"},"match":{"location":"karate","arguments":[]},"keyword":"And","line":96},{"name":"method POST","result":{"duration":1478659167,"status":"passed"},"match":{"location":"karate","arguments":[]},"keyword":"When","line":97},{"name":"status 400","result":{"duration":3500,"status":"passed"},"match":{"location":"karate","arguments":[]},"keyword":"Then","line":98},{"name":"print 'customer create with wrong data response -->',response","result":{"duration":2603917,"status":"passed"},"match":{"location":"karate","arguments":[]},"keyword":"Then","line":99,"doc_string":{"content_type":"","value":"15:28:05.242 [print] customer create with wrong data response --> {\n  \"visible\": true,\n  \"action\": \"default\",\n  \"messages\": [\n    \"Phone.AlreadyUsed\",\n    \"Required\",\n    \"be.user.length\"\n  ],\n  \"validations\": {\n    \"phoneNumber\": [\n      \"Phone.AlreadyUsed\",\n      \"Required\",\n      \"be.user.length\"\n    ]\n  },\n  \"type\": \"validation\",\n  \"title\": null,\n  \"message\": \"Phone.AlreadyUsed\",\n  \"typeCode\": 400\n}\n \n","line":99}},{"name":"match response.message contains 'Phone.AlreadyUsed'","result":{"duration":271459,"status":"passed"},"match":{"location":"karate","arguments":[]},"keyword":"Then","line":100}],"tags":[]},{"line":3,"name":"","description":"","type":"background","keyword":"Background","steps":[{"name":"url userApiUrl","result":{"duration":8209,"status":"passed"},"match":{"location":"karate","arguments":[]},"keyword":"*","line":4,"doc_string":{"content_type":"","value":"15:28:04.089 Environment variable is : popcorn \n","line":4}},{"name":"header Content-Type = 'application\/json-patch+json'","result":{"duration":40959,"status":"passed"},"match":{"location":"karate","arguments":[]},"keyword":"*","line":5},{"name":"header accept = '*\/*'","result":{"duration":14333,"status":"passed"},"match":{"location":"karate","arguments":[]},"keyword":"*","line":6},{"name":"def randomString = Java.type('utils.RandomValue')","result":{"duration":141375,"status":"passed"},"match":{"location":"karate","arguments":[]},"keyword":"*","line":8},{"name":"def randomEmailValue = new randomString().createRandomString(7,\"email\");","result":{"duration":1012667,"status":"passed"},"match":{"location":"karate","arguments":[]},"keyword":"*","line":9},{"name":"def randomStringValue = new randomString().createRandomString(7,\"string\");","result":{"duration":231292,"status":"passed"},"match":{"location":"karate","arguments":[]},"keyword":"*","line":10},{"name":"def randomIntValue = new randomString().createInt(10);","result":{"duration":91959,"status":"passed"},"match":{"location":"karate","arguments":[]},"keyword":"*","line":11}]},{"line":106,"name":"Customer Create - Fail Scenarios","description":"","id":"customer-create---fail-scenarios","type":"scenario","keyword":"Scenario Outline","steps":[{"name":"path '\/Customer\/Create'","result":{"duration":52500,"status":"passed"},"match":{"location":"karate","arguments":[]},"keyword":"Given","line":85},{"name":"header Authorization = 'Bearer ' + consoleAuthorization","result":{"duration":41166,"status":"passed"},"match":{"location":"karate","arguments":[]},"keyword":"And","line":86},{"name":"def customerCreateInfo =","result":{"duration":1564334,"status":"passed"},"match":{"location":"karate","arguments":[]},"keyword":"*","line":87,"doc_string":{"content_type":"","value":"{\n   \"fullName\": \"#(randomStringValue)\",\n   \"phoneCountryId\": \"59c4edba-f347-45b3-a5c9-aed7ac852ff8\",\n   \"email\": \"#(randomEmailValue)\",\n   \"phoneNumber\": \"wrongwrong\"\n}","line":87}},{"name":"request customerCreateInfo","result":{"duration":9458,"status":"passed"},"match":{"location":"karate","arguments":[]},"keyword":"And","line":96},{"name":"method POST","result":{"duration":841826750,"status":"passed"},"match":{"location":"karate","arguments":[]},"keyword":"When","line":97},{"name":"status 400","result":{"duration":5042,"status":"passed"},"match":{"location":"karate","arguments":[]},"keyword":"Then","line":98},{"name":"print 'customer create with wrong data response -->',response","result":{"duration":1482500,"status":"passed"},"match":{"location":"karate","arguments":[]},"keyword":"Then","line":99,"doc_string":{"content_type":"","value":"15:28:04.937 [print] customer create with wrong data response --> {\n  \"visible\": true,\n  \"action\": \"default\",\n  \"messages\": [\n    \"Phone.AlreadyUsed\"\n  ],\n  \"validations\": {\n    \"phoneNumber\": [\n      \"Phone.AlreadyUsed\"\n    ]\n  },\n  \"type\": \"validation\",\n  \"title\": null,\n  \"message\": \"Phone.AlreadyUsed\",\n  \"typeCode\": 400\n}\n \n","line":99}},{"name":"match response.message contains 'Phone.AlreadyUsed'","result":{"duration":2163583,"status":"passed"},"match":{"location":"karate","arguments":[]},"keyword":"Then","line":100}],"tags":[]},{"line":3,"name":"","description":"","type":"background","keyword":"Background","steps":[{"name":"url userApiUrl","result":{"duration":8542,"status":"passed"},"match":{"location":"karate","arguments":[]},"keyword":"*","line":4,"doc_string":{"content_type":"","value":"15:28:04.536 Environment variable is : popcorn \n","line":4}},{"name":"header Content-Type = 'application\/json-patch+json'","result":{"duration":34917,"status":"passed"},"match":{"location":"karate","arguments":[]},"keyword":"*","line":5},{"name":"header accept = '*\/*'","result":{"duration":15250,"status":"passed"},"match":{"location":"karate","arguments":[]},"keyword":"*","line":6},{"name":"def randomString = Java.type('utils.RandomValue')","result":{"duration":566334,"status":"passed"},"match":{"location":"karate","arguments":[]},"keyword":"*","line":8},{"name":"def randomEmailValue = new randomString().createRandomString(7,\"email\");","result":{"duration":494166,"status":"passed"},"match":{"location":"karate","arguments":[]},"keyword":"*","line":9},{"name":"def randomStringValue = new randomString().createRandomString(7,\"string\");","result":{"duration":170750,"status":"passed"},"match":{"location":"karate","arguments":[]},"keyword":"*","line":10},{"name":"def randomIntValue = new randomString().createInt(10);","result":{"duration":81625,"status":"passed"},"match":{"location":"karate","arguments":[]},"keyword":"*","line":11}]},{"line":107,"name":"Customer Create - Fail Scenarios","description":"","id":"customer-create---fail-scenarios","type":"scenario","keyword":"Scenario Outline","steps":[{"name":"path '\/Customer\/Create'","result":{"duration":63875,"status":"passed"},"match":{"location":"karate","arguments":[]},"keyword":"Given","line":85},{"name":"header Authorization = 'Bearer ' + consoleAuthorization","result":{"duration":164125,"status":"passed"},"match":{"location":"karate","arguments":[]},"keyword":"And","line":86},{"name":"def customerCreateInfo =","result":{"duration":146750,"status":"passed"},"match":{"location":"karate","arguments":[]},"keyword":"*","line":87,"doc_string":{"content_type":"","value":"{\n   \"fullName\": \"#(randomStringValue)\",\n   \"phoneCountryId\": \"59c4edba-f347-45b3-a5c9-aed7ac852ff8\",\n   \"email\": \"abc\",\n   \"phoneNumber\": \"#(randomIntValue)\"\n}","line":87}},{"name":"request customerCreateInfo","result":{"duration":3417,"status":"passed"},"match":{"location":"karate","arguments":[]},"keyword":"And","line":96},{"name":"method POST","result":{"duration":655779458,"status":"passed"},"match":{"location":"karate","arguments":[]},"keyword":"When","line":97},{"name":"status 400","result":{"duration":36292,"status":"passed"},"match":{"location":"karate","arguments":[]},"keyword":"Then","line":98},{"name":"print 'customer create with wrong data response -->',response","result":{"duration":9798209,"status":"passed"},"match":{"location":"karate","arguments":[]},"keyword":"Then","line":99,"doc_string":{"content_type":"","value":"15:28:05.210 [print] customer create with wrong data response --> {\n  \"visible\": true,\n  \"action\": \"default\",\n  \"messages\": [\n    \"Email.NotValid\",\n    \"be.user.length\"\n  ],\n  \"validations\": {\n    \"email\": [\n      \"Email.NotValid\",\n      \"be.user.length\"\n    ]\n  },\n  \"type\": \"validation\",\n  \"title\": null,\n  \"message\": \"Email.NotValid\",\n  \"typeCode\": 400\n}\n \n","line":99}},{"name":"match response.message contains 'Email.NotValid'","result":{"duration":2864333,"status":"passed"},"match":{"location":"karate","arguments":[]},"keyword":"Then","line":100}],"tags":[]},{"line":3,"name":"","description":"","type":"background","keyword":"Background","steps":[{"name":"url userApiUrl","result":{"duration":13291,"status":"passed"},"match":{"location":"karate","arguments":[]},"keyword":"*","line":4,"doc_string":{"content_type":"","value":"15:28:04.899 Environment variable is : popcorn \n","line":4}},{"name":"header Content-Type = 'application\/json-patch+json'","result":{"duration":127917,"status":"passed"},"match":{"location":"karate","arguments":[]},"keyword":"*","line":5},{"name":"header accept = '*\/*'","result":{"duration":43500,"status":"passed"},"match":{"location":"karate","arguments":[]},"keyword":"*","line":6},{"name":"def randomString = Java.type('utils.RandomValue')","result":{"duration":719084,"status":"passed"},"match":{"location":"karate","arguments":[]},"keyword":"*","line":8},{"name":"def randomEmailValue = new randomString().createRandomString(7,\"email\");","result":{"duration":603083,"status":"passed"},"match":{"location":"karate","arguments":[]},"keyword":"*","line":9},{"name":"def randomStringValue = new randomString().createRandomString(7,\"string\");","result":{"duration":245417,"status":"passed"},"match":{"location":"karate","arguments":[]},"keyword":"*","line":10},{"name":"def randomIntValue = new randomString().createInt(10);","result":{"duration":331542,"status":"passed"},"match":{"location":"karate","arguments":[]},"keyword":"*","line":11}]},{"line":108,"name":"Customer Create - Fail Scenarios","description":"","id":"customer-create---fail-scenarios","type":"scenario","keyword":"Scenario Outline","steps":[{"name":"path '\/Customer\/Create'","result":{"duration":955208,"status":"passed"},"match":{"location":"karate","arguments":[]},"keyword":"Given","line":85},{"name":"header Authorization = 'Bearer ' + consoleAuthorization","result":{"duration":124625,"status":"passed"},"match":{"location":"karate","arguments":[]},"keyword":"And","line":86},{"name":"def customerCreateInfo =","result":{"duration":358375,"status":"passed"},"match":{"location":"karate","arguments":[]},"keyword":"*","line":87,"doc_string":{"content_type":"","value":"{\n   \"fullName\": \"#(randomStringValue)\",\n   \"phoneCountryId\": \"\",\n   \"email\": \"#(randomEmailValue)\",\n   \"phoneNumber\": \"#(randomIntValue)\"\n}","line":87}},{"name":"request customerCreateInfo","result":{"duration":7333,"status":"passed"},"match":{"location":"karate","arguments":[]},"keyword":"And","line":96},{"name":"method POST","result":{"duration":605305500,"status":"passed"},"match":{"location":"karate","arguments":[]},"keyword":"When","line":97},{"name":"status 400","result":{"duration":8667,"status":"passed"},"match":{"location":"karate","arguments":[]},"keyword":"Then","line":98},{"name":"print 'customer create with wrong data response -->',response","result":{"duration":1551917,"status":"passed"},"match":{"location":"karate","arguments":[]},"keyword":"Then","line":99,"doc_string":{"content_type":"","value":"15:28:05.510 [print] customer create with wrong data response --> {\n  \"visible\": true,\n  \"action\": \"default\",\n  \"messages\": [\n    \"Error converting value \\\"\\\" to type 'System.Guid'. Path 'phoneCountryId', line 1, position 41.\"\n  ],\n  \"validations\": {\n    \"phoneCountryId\": [\n      \"Error converting value \\\"\\\" to type 'System.Guid'. Path 'phoneCountryId', line 1, position 41.\"\n    ]\n  },\n  \"type\": \"validation\",\n  \"title\": null,\n  \"message\": \"Error converting value \\\"\\\" to type 'System.Guid'. Path 'phoneCountryId', line 1, position 41.\",\n  \"typeCode\": 400\n}\n \n","line":99}},{"name":"match response.message contains 'Error converting value'","result":{"duration":258667,"status":"passed"},"match":{"location":"karate","arguments":[]},"keyword":"Then","line":100}],"tags":[]},{"line":3,"name":"","description":"","type":"background","keyword":"Background","steps":[{"name":"url userApiUrl","result":{"duration":7416,"status":"passed"},"match":{"location":"karate","arguments":[]},"keyword":"*","line":4,"doc_string":{"content_type":"","value":"15:28:04.942 Environment variable is : popcorn \n","line":4}},{"name":"header Content-Type = 'application\/json-patch+json'","result":{"duration":18167,"status":"passed"},"match":{"location":"karate","arguments":[]},"keyword":"*","line":5},{"name":"header accept = '*\/*'","result":{"duration":11208,"status":"passed"},"match":{"location":"karate","arguments":[]},"keyword":"*","line":6},{"name":"def randomString = Java.type('utils.RandomValue')","result":{"duration":97375,"status":"passed"},"match":{"location":"karate","arguments":[]},"keyword":"*","line":8},{"name":"def randomEmailValue = new randomString().createRandomString(7,\"email\");","result":{"duration":121416,"status":"passed"},"match":{"location":"karate","arguments":[]},"keyword":"*","line":9},{"name":"def randomStringValue = new randomString().createRandomString(7,\"string\");","result":{"duration":48208,"status":"passed"},"match":{"location":"karate","arguments":[]},"keyword":"*","line":10},{"name":"def randomIntValue = new randomString().createInt(10);","result":{"duration":48625,"status":"passed"},"match":{"location":"karate","arguments":[]},"keyword":"*","line":11}]},{"line":109,"name":"Customer Create - Fail Scenarios","description":"","id":"customer-create---fail-scenarios","type":"scenario","keyword":"Scenario Outline","steps":[{"name":"path '\/Customer\/Create'","result":{"duration":40375,"status":"passed"},"match":{"location":"karate","arguments":[]},"keyword":"Given","line":85},{"name":"header Authorization = 'Bearer ' + consoleAuthorization","result":{"duration":28625,"status":"passed"},"match":{"location":"karate","arguments":[]},"keyword":"And","line":86},{"name":"def customerCreateInfo =","result":{"duration":627334,"status":"passed"},"match":{"location":"karate","arguments":[]},"keyword":"*","line":87,"doc_string":{"content_type":"","value":"{\n   \"fullName\": \"#(randomStringValue)\",\n   \"phoneCountryId\": \"wrong\",\n   \"email\": \"#(randomEmailValue)\",\n   \"phoneNumber\": \"#(randomIntValue)\"\n}","line":87}},{"name":"request customerCreateInfo","result":{"duration":3292,"status":"passed"},"match":{"location":"karate","arguments":[]},"keyword":"And","line":96},{"name":"method POST","result":{"duration":565112917,"status":"passed"},"match":{"location":"karate","arguments":[]},"keyword":"When","line":97},{"name":"status 400","result":{"duration":5333,"status":"passed"},"match":{"location":"karate","arguments":[]},"keyword":"Then","line":98},{"name":"print 'customer create with wrong data response -->',response","result":{"duration":1446667,"status":"passed"},"match":{"location":"karate","arguments":[]},"keyword":"Then","line":99,"doc_string":{"content_type":"","value":"15:28:05.510 [print] customer create with wrong data response --> {\n  \"visible\": true,\n  \"action\": \"default\",\n  \"messages\": [\n    \"Error converting value \\\"wrong\\\" to type 'System.Guid'. Path 'phoneCountryId', line 1, position 46.\"\n  ],\n  \"validations\": {\n    \"phoneCountryId\": [\n      \"Error converting value \\\"wrong\\\" to type 'System.Guid'. Path 'phoneCountryId', line 1, position 46.\"\n    ]\n  },\n  \"type\": \"validation\",\n  \"title\": null,\n  \"message\": \"Error converting value \\\"wrong\\\" to type 'System.Guid'. Path 'phoneCountryId', line 1, position 46.\",\n  \"typeCode\": 400\n}\n \n","line":99}},{"name":"match response.message contains 'Error converting value'","result":{"duration":170375,"status":"passed"},"match":{"location":"karate","arguments":[]},"keyword":"Then","line":100}],"tags":[]}],"name":"features\/userApi\/customer\/customer_create.feature","description":"Customer Create","id":"customer-create","keyword":"Feature","uri":"features\/userApi\/customer\/customer_create.feature"}]